<?xml version="1.0" encoding="UTF-8"?>
<metadata xml:lang="en"><Esri><CreaDate>20250225</CreaDate><CreaTime>18341200</CreaTime><ArcGISFormat>1.0</ArcGISFormat><SyncOnce>TRUE</SyncOnce><DataProperties><lineage><Process ToolSource="c:\program files\arcgis\pro\Resources\ArcToolbox\toolboxes\Conversion Tools.tbx\FeatureToRaster" Date="20250225" Time="183412">FeatureToRaster C:\Users\olley\Documents\ArcGIS\Projects\SeagrassDatasets\Polygon_Substrate\6.shp Substrate C:\Users\olley\Documents\ArcGIS\Projects\SeagrassDatasets\Polygon_Substrate\rasters\6.tif 7.48016462252963E-04</Process></lineage><LayerFile>{"type":"CIMLayerDocument","version":"3.2.0","build":49743,"layers":["CIMPATH=map/6_tif.json"],"layerDefinitions":[{"type":"CIMRasterLayer","name":"6.tif","uRI":"CIMPATH=map/6_tif.json","sourceModifiedTime":{"type":"TimeInstant"},"useSourceMetadata":true,"description":"6.tif","layerElevation":{"type":"CIMLayerElevationSurface","elevationSurfaceLayerURI":"CIMPATH=Map/1ce7c1d4ee6349aeac61255ea83391e9.json"},"expanded":true,"layerType":"Operational","showLegends":true,"visibility":true,"displayCacheType":"Permanent","maxDisplayCacheAge":5,"showPopups":true,"serviceLayerID":-1,"refreshRate":-1,"refreshRateUnit":"esriTimeUnitsSeconds","blendingMode":"Alpha","allowDrapingOnIntegratedMesh":true,"dataConnection":{"type":"CIMStandardDataConnection"},"colorizer":{"type":"CIMRasterUniqueValueColorizer","resamplingType":"NearestNeighbor","fieldName":"Substrate","groups":[{"type":"CIMRasterUniqueValueGroup","classes":[{"type":"CIMRasterUniqueValueClass","values":["Sand"],"label":"Sand","color":{"type":"CIMRGBColor","values":[193.699999999999989,88.069999999999993,99.849999999999994,100]}},{"type":"CIMRasterUniqueValueClass","values":["Coarse substrate"],"label":"Coarse substrate","color":{"type":"CIMRGBColor","values":[100.790000000000006,241.610000000000014,95.370000000000005,100]}},{"type":"CIMRasterUniqueValueClass","values":["Mixed sediment"],"label":"Mixed sediment","color":{"type":"CIMRGBColor","values":[88.530000000000001,202.52000000000001,251.300000000000011,100]}},{"type":"CIMRasterUniqueValueClass","values":["Rock or other hard substrata"],"label":"Rock or other hard substrata","color":{"type":"CIMRGBColor","values":[107.14,83.719999999999999,241.97,100]}},{"type":"CIMRasterUniqueValueClass","values":["Seabed"],"label":"Seabed","color":{"type":"CIMRGBColor","values":[238.81,222.52000000000001,158.19,100]}},{"type":"CIMRasterUniqueValueClass","values":["Sediment"],"label":"Sediment","color":{"type":"CIMRGBColor","values":[63.460000000000001,73.060000000000002,129.460000000000008,100]}}],"heading":"Substrate"}],"colorRamp":{"type":"CIMRandomHSVColorRamp","colorSpace":{"type":"CIMICCColorSpace","url":"Default RGB"},"maxH":360,"minS":33,"maxS":66,"minV":50,"maxV":99,"minAlpha":100,"maxAlpha":100}},"attributeTable":{"type":"CIMRasterTable","displayField":"Substrate","editable":true}}]}</LayerFile></DataProperties></Esri></metadata>
